asgi_gzip/__init__.py
asgi_gzip/headers.py
asgi_gzip-0.2.dist-info/LICENSE
asgi_gzip-0.2.dist-info/METADATA
asgi_gzip-0.2.dist-info/WHEEL
asgi_gzip-0.2.dist-info/top_level.txt
asgi_gzip-0.2.dist-info/RECORD
