Metadata-Version: 2.1
Name: asgi-gzip
Version: 0.2
Summary: gzip middleware for ASGI applications, extracted from Starlette
Home-page: https://github.com/simonw/asgi-gzip
Author: Simon Willison
License: BSD
Project-URL: Issues, https://github.com/simonw/asgi-gzip/issues
Project-URL: CI, https://github.com/simonw/asgi-gzip/actions
Project-URL: Changelog, https://github.com/simonw/asgi-gzip/releases
Requires-Python: >=3.7
License-File: LICENSE
Provides-Extra: test
Requires-Dist: pytest ; extra == 'test'
Requires-Dist: starlette ; extra == 'test'
Requires-Dist: requests ; extra == 'test'
Requires-Dist: trio ; extra == 'test'
Requires-Dist: httpx ; extra == 'test'
